arpakana/__init__.py
arpakana/arpabet.py
arpakana/py.typed
arpakana/schemas.py
arpakana-0.0.3.dist-info/METADATA
arpakana-0.0.3.dist-info/WHEEL
arpakana-0.0.3.dist-info/licenses/LICENSE
arpakana-0.0.3.dist-info/RECORD
