Metadata-Version: 2.4
Name: arpakana
Version: 0.0.3
Summary: A modern Python project template optimized for Claude Code with strict guardrails
License-File: LICENSE
Requires-Python: >=3.12
Requires-Dist: pydantic>=2.11.7
Requires-Dist: rich>=13.7.0
Requires-Dist: structlog>=25.4.0
